memory_machine/__init__.py
memory_machine/githf.py
memory_machine/machina.yaml
memory_machine-0.0.3.dist-info/LICENSE
memory_machine-0.0.3.dist-info/METADATA
memory_machine-0.0.3.dist-info/WHEEL
memory_machine-0.0.3.dist-info/top_level.txt
memory_machine-0.0.3.dist-info/RECORD
